cpidk/__init__.py
cpidk/exceptions.py
cpidk/helper.py
cpidk/model.py
cpidk-1.0.2.dist-info/LICENSE
cpidk-1.0.2.dist-info/METADATA
cpidk-1.0.2.dist-info/WHEEL
cpidk-1.0.2.dist-info/RECORD
