Metadata-Version: 2.3
Name: cpidk
Version: 1.0.2
Summary: A Python library for checking driver permissions in Poland.
License: MIT
Keywords: cpidk,cepik,driver,driver-license
Author: deestt
Requires-Python: >=3.8,<4.0
Classifier: License :: OSI Approved :: MIT License
Classifier: Programming Language :: Python :: 3
Classifier: Programming Language :: Python :: 3.8
Classifier: Programming Language :: Python :: 3.9
Classifier: Programming Language :: Python :: 3.10
Classifier: Programming Language :: Python :: 3.11
Classifier: Programming Language :: Python :: 3.12
Classifier: Programming Language :: Python :: 3.13
Requires-Dist: pydantic (>2.2.0)
Requires-Dist: requests (>2.0.0)
